setup.py
omuliga_matrix/Generalmatrix.py
omuliga_matrix/MatrixOps.py
omuliga_matrix/__init__.py
omuliga_matrix.egg-info/PKG-INFO
omuliga_matrix.egg-info/SOURCES.txt
omuliga_matrix.egg-info/dependency_links.txt
omuliga_matrix.egg-info/not-zip-safe
omuliga_matrix.egg-info/top_level.txt