Metadata-Version: 1.0
Name: omuliga-matrix
Version: 0.1
Summary: Matrix Operations
Home-page: UNKNOWN
Author: Olivia Nabbosa
Author-email: olivia.nabbosa@outlook.com
License: UNKNOWN
Platform: UNKNOWN
